CHANGES.txt
MANIFEST.in
README.md
setup.py
django_pages/__init__.py
django_pages/admin.py
django_pages/context.py
django_pages/dashboard.py
django_pages/settings.py
django_pages/tests.py
django_pages/urls.py
django_pages/views.py
django_pages.egg-info/PKG-INFO
django_pages.egg-info/SOURCES.txt
django_pages.egg-info/dependency_links.txt
django_pages.egg-info/not-zip-safe
django_pages.egg-info/requires.txt
django_pages.egg-info/top_level.txt
django_pages/comments/__init__.py
django_pages/comments/admin.py
django_pages/comments/forms.py
django_pages/comments/models.py
django_pages/comments/validators.py
django_pages/common/__init__.py
django_pages/common/admin_actions.py
django_pages/common/errors.py
django_pages/feed/__init__.py
django_pages/feed/admin.py
django_pages/feed/feed.py
django_pages/feed/models.py
django_pages/language/__init__.py
django_pages/language/admin.py
django_pages/language/models.py
django_pages/locale/cs_CZ/LC_MESSAGES/django.mo
django_pages/locale/cs_CZ/LC_MESSAGES/django.po
django_pages/log/__init__.py
django_pages/log/middleware.py
django_pages/looks/__init__.py
django_pages/looks/admin.py
django_pages/looks/models.py
django_pages/menu/__init__.py
django_pages/menu/admin.py
django_pages/menu/models.py
django_pages/metadata/__init__.py
django_pages/metadata/admin.py
django_pages/metadata/models.py
django_pages/pages/__init__.py
django_pages/pages/admin.py
django_pages/pages/models.py
django_pages/site/__init__.py
django_pages/site/admin.py
django_pages/site/models.py
django_pages/static/admin/img/arrow-down.png
django_pages/static/admin/img/arrow-up.png
django_pages/static/admin/js/ckeditor/build-config.js
django_pages/static/admin/js/ckeditor/ckeditor.js
django_pages/static/admin/js/ckeditor/contents.css
django_pages/static/admin/js/ckeditor/start.js
django_pages/static/admin/js/ckeditor/styles.js
django_pages/static/admin/js/ckeditor/adapters/jquery.js
django_pages/static/admin/js/ckeditor/lang/cs.js
django_pages/static/admin/js/ckeditor/lang/en.js
django_pages/static/admin/js/ckeditor/plugins/icons.png
django_pages/static/admin/js/ckeditor/plugins/icons_hidpi.png
django_pages/static/admin/js/ckeditor/plugins/a11yhelp/dialogs/a11yhelp.js
