Metadata-Version: 1.0
Name: django-pages
Version: 1.4.0
Summary: Simple CMS for django
Home-page: https://github.com/lunemec/django-pages
Author: Lukas Nemec
Author-email: lu.nemec@gmail.com
License: see LICENSE.txt
Platform: UNKNOWN
